MANIFEST.in
awg.py
setup.py
awg-data/main.css
awg-data/settings.json
awg-data/default_template/footer.tpl
awg-data/default_template/header.tpl
awg-data/default_template/index.tpl
awg-data/default_template/repo.tpl
awg.egg-info/PKG-INFO
awg.egg-info/SOURCES.txt
awg.egg-info/dependency_links.txt
awg.egg-info/entry_points.txt
awg.egg-info/not-zip-safe
awg.egg-info/requires.txt
awg.egg-info/top_level.txt